<?xml version="1.0" encoding="utf-8"?>
<!--Detailed report on module FileClient-->
<CCCC_Project>
<module_summary>
<lines_of_code value="101" level="0" />
<lines_of_code_per_member_function value="******" level="0" />
<McCabes_cyclomatic_complexity value="20" level="0" />
<McCabes_cyclomatic_complexity_per_member_function value="******" level="2" />
<lines_of_code value="9" level="0" />
<lines_of_code_per_member_function value="********" level="2" />
<lines_of_code_per_line_of_comment value="11.222" level="1" />
<McCabes_cyclomatic_complexity_per_line_of_comment value="2.222" level="0" />
<weighted_methods_per_class_unity value="6" level="0" />
<weighted_methods_per_class_visibility value="5" level="0" />
<depth_of_inheritance_tree value="0" level="0" />
<number_of_children value="0" level="0" />
<coupling_between_objects value="1" level="0" />
<IF4 value="0" level="0" />
<IF4_per_member_function value="********" level="0" />
<IF4_visible value="0" level="0" />
<IF4_visible_per_member_function value="********" level="0" />
<IF4_concrete value="0" level="0" />
<IF4_concrete_per_member_function value="********" level="0" />
</module_summary>
<module_detail>
<description>definition</description>
<source_reference file="FileClient.h" line="45" />
<lines_of_code value="10" level="0" />
<McCabes_cyclomatic_complexity value="0" level="0" />
<lines_of_comment value="3" level="0" />
<lines_of_code_per_line_of_comment value="------" level="0" />
<McCabes_cyclomatic_complexity_per_line_of_comment value="------" level="0" />
</module_detail>
<procedural_detail>
<member_function>
<name>FileClient()</name>
<extent>
<description>definition</description>
<source_reference file="FileClient.cpp" line="58" />
</extent>
<extent>
<description>declaration</description>
<source_reference file="FileClient.h" line="47" />
</extent>
<lines_of_code value="3" level="0" />
<McCabes_cyclomatic_complexity value="0" level="0" />
<lines_of_comment value="0" level="0" />
<lines_of_code_per_line_of_comment value="------" level="0" />
<McCabes_cyclomatic_complexity_per_line_of_comment value="------" level="0" />
</member_function>
<member_function>
<name>FileClient(const string &amp;,const string &amp;,const string &amp;,const string &amp;)</name>
<extent>
<description>definition</description>
<source_reference file="FileClient.cpp" line="61" />
</extent>
<extent>
<description>declaration</description>
<source_reference file="FileClient.h" line="48" />
</extent>
<lines_of_code value="7" level="0" />
<McCabes_cyclomatic_complexity value="0" level="0" />
<lines_of_comment value="0" level="0" />
<lines_of_code_per_line_of_comment value="------" level="0" />
<McCabes_cyclomatic_complexity_per_line_of_comment value="------" level="0" />
</member_function>
<member_function>
<name>getFileFromZHT()</name>
<extent>
<description>definition</description>
<source_reference file="FileClient.cpp" line="70" />
</extent>
<extent>
<description>declaration</description>
<source_reference file="FileClient.h" line="53" />
</extent>
<lines_of_code value="11" level="0" />
<McCabes_cyclomatic_complexity value="1" level="0" />
<lines_of_comment value="0" level="0" />
<lines_of_code_per_line_of_comment value="------" level="0" />
<McCabes_cyclomatic_complexity_per_line_of_comment value="------" level="0" />
</member_function>
<member_function>
<name>getFileFromZHTInternal2(const int &amp;,const char **)</name>
<extent>
<description>definition</description>
<source_reference file="FileClient.cpp" line="95" />
</extent>
<extent>
<description>declaration</description>
<source_reference file="FileClient.h" line="57" />
</extent>
<lines_of_code value="58" level="1" />
<McCabes_cyclomatic_complexity value="18" level="1" />
<lines_of_comment value="6" level="0" />
<lines_of_code_per_line_of_comment value="9.667" level="1" />
<McCabes_cyclomatic_complexity_per_line_of_comment value="3.000" level="0" />
</member_function>
<member_function>
<name>putFileToZHT()</name>
<extent>
<description>definition</description>
<source_reference file="FileClient.cpp" line="84" />
</extent>
<extent>
<description>declaration</description>
<source_reference file="FileClient.h" line="54" />
</extent>
<lines_of_code value="9" level="0" />
<McCabes_cyclomatic_complexity value="1" level="0" />
<lines_of_comment value="0" level="0" />
<lines_of_code_per_line_of_comment value="------" level="0" />
<McCabes_cyclomatic_complexity_per_line_of_comment value="------" level="0" />
</member_function>
<member_function>
<name>~FileClient()</name>
<extent>
<description>definition</description>
<source_reference file="FileClient.cpp" line="67" />
</extent>
<extent>
<description>declaration</description>
<source_reference file="FileClient.h" line="51" />
</extent>
<lines_of_code value="3" level="0" />
<McCabes_cyclomatic_complexity value="0" level="0" />
<lines_of_comment value="0" level="0" />
<lines_of_code_per_line_of_comment value="------" level="0" />
<McCabes_cyclomatic_complexity_per_line_of_comment value="------" level="0" />
</member_function>
</procedural_detail>
<structural_detail>
<module>
<name>FileClient</name>
<client_module>
</client_module>
<supplier_module>
<name>string</name>
<visible>true</visible>
<concrete>true</concrete>
<extent>
<description>pass by reference</description>
<source_reference file="FileClient.cpp" line="61" />
</extent>
<extent>
<description>pass by reference</description>
<source_reference file="FileClient.cpp" line="61" />
</extent>
<extent>
<description>pass by reference</description>
<source_reference file="FileClient.cpp" line="62" />
</extent>
<extent>
<description>pass by reference</description>
<source_reference file="FileClient.cpp" line="62" />
</extent>
<extent>
<description>pass by reference</description>
<source_reference file="FileClient.h" line="48" />
</extent>
<extent>
<description>pass by reference</description>
<source_reference file="FileClient.h" line="48" />
</extent>
<extent>
<description>pass by reference</description>
<source_reference file="FileClient.h" line="49" />
</extent>
<extent>
<description>pass by reference</description>
<source_reference file="FileClient.h" line="49" />
</extent>
<extent>
<description>has by value</description>
<source_reference file="FileClient.h" line="60" />
</extent>
<extent>
<description>has by value</description>
<source_reference file="FileClient.h" line="61" />
</extent>
<extent>
<description>has by value</description>
<source_reference file="FileClient.h" line="62" />
</extent>
<extent>
<description>has by value</description>
<source_reference file="FileClient.h" line="63" />
</extent>
<extent>
<description>has by value</description>
<source_reference file="FileClient.h" line="64" />
</extent>
</supplier_module>
</module>
</structural_detail>
</CCCC_Project>
